neet/__init__.py
neet/draw.py
neet/exceptions.py
neet/information.py
neet/landscape.py
neet/network.py
neet/python.py
neet/statespace.py
neet/boolean/__init__.py
neet/boolean/conv.py
neet/boolean/eca.py
neet/boolean/examples.py
neet/boolean/logicnetwork.py
neet/boolean/network.py
neet/boolean/reca.py
neet/boolean/sensitivity.py
neet/boolean/wtnetwork.py
neet/boolean/data/c_elegans-edges.dat
neet/boolean/data/c_elegans-nodes.dat
neet/boolean/data/hgf-signaling-expressions.txt
neet/boolean/data/hgf-signaling-external.txt
neet/boolean/data/il-6-signaling-expressions.txt
neet/boolean/data/il-6-signaling-external.txt
neet/boolean/data/mouse_cortical_fig_7B-logic_expressions.txt
neet/boolean/data/mouse_cortical_fig_7B-truth_table.txt
neet/boolean/data/mouse_cortical_fig_7C-logic_expressions.txt
neet/boolean/data/mouse_cortical_fig_7C-truth_table.txt
neet/boolean/data/myeloid-logic_expressions.txt
neet/boolean/data/myeloid-truth_table.txt
neet/boolean/data/p53_dmg-edges.txt
neet/boolean/data/p53_dmg-nodes.txt
neet/boolean/data/p53_no_dmg-edges.txt
neet/boolean/data/p53_no_dmg-nodes.txt
neet/boolean/data/s_cerevisiae-edges.txt
neet/boolean/data/s_cerevisiae-nodes.txt
neet/boolean/data/s_pombe-edges.txt
neet/boolean/data/s_pombe-nodes.txt
neet-1.0.0.dist-info/LICENSE
neet-1.0.0.dist-info/METADATA
neet-1.0.0.dist-info/WHEEL
neet-1.0.0.dist-info/top_level.txt
neet-1.0.0.dist-info/RECORD
