Metadata-Version: 2.1
Name: neet
Version: 1.0.0
Summary: Simulating and analyzing network models
Home-page: https://github.com/elife-asu/neet
Maintainer: Douglas G. Moore
Maintainer-email: doug@dglmoore.com
License: MIT License
Requires-Dist: deprecated
Requires-Dist: networkx
Requires-Dist: numpy
Requires-Dist: pyinform
Requires-Dist: six
